{
  "project_info": {
    "project_number": "694262452236",
    "project_id": "jamia-85237",
    "storage_bucket": "jamia-85237.appspot.com"
  },
  "client": [
    {
      "client_info": {
        "mobilesdk_app_id": "1:694262452236:android:f2bcf551f0f1ec435f9e29",
        "android_client_info": {
          "package_name": "com.example.create_jamia"
        }
      },
      "oauth_client": [
        {
          "client_id": "694262452236-dcvcu5rt49h95tqll5ptdjna8jcfqevl.apps.googleusercontent.com",
          "client_type": 3
        }
      ],
      "api_key": [
        {
          "current_key": "AIzaSyBI801lXo8egC9zyV4ZohfT3ePdZvrEpuU"
        }
      ],
      "services": {
        "appinvite_service": {
          "other_platform_oauth_client": [
            {
              "client_id": "694262452236-dcvcu5rt49h95tqll5ptdjna8jcfqevl.apps.googleusercontent.com",
              "client_type": 3
            }
          ]
        }
      }
    }
  ],
  "configuration_version": "1"
}